fscrawler/__init__.py
fscrawler/_version.py
fscrawler/crawler.py
fscrawler/validator.py
fscrawler/controller/__init__.py
fscrawler/controller/fsapi.py
fscrawler/controller/graph_io.py
fscrawler/controller/graph_reader.py
fscrawler/controller/graph_validator.py
fscrawler/controller/graph_writer.py
fscrawler/controller/relationship_rewriter.py
fscrawler/controller/session.py
fscrawler/model/__init__.py
fscrawler/model/graph.py
fscrawler/model/graph_db_impl.py
fscrawler/model/graph_memory_impl.py
fscrawler/model/individual.py
fscrawler/model/name.py
fscrawler/model/relationship_types.py
fscrawler/util/__init__.py
fscrawler/util/abstract_graph.py
fscrawler/util/db_reader.py
fs_crawler-0.3.2.dist-info/LICENSE
fs_crawler-0.3.2.dist-info/METADATA
fs_crawler-0.3.2.dist-info/WHEEL
fs_crawler-0.3.2.dist-info/entry_points.txt
fs_crawler-0.3.2.dist-info/top_level.txt
fs_crawler-0.3.2.dist-info/RECORD
